scanpy_clustering/__init__.py
scanpy_clustering/clustering.py
scanpy_clustering/_c_ext/__init__.py
scanpy_clustering/algorithms/KMeans.py
scanpy_clustering/algorithms/__init__.py
scanpy_clustering/algorithms/base.py
scanpy_clustering/algorithms/dbScan.py
scanpy_clustering/algorithms/dbScan_Base.py
scanpy_clustering/algorithms/hdbScan.py
rna_clustering_algorithms-0.1.4.dist-info/LICENSE
rna_clustering_algorithms-0.1.4.dist-info/METADATA
rna_clustering_algorithms-0.1.4.dist-info/WHEEL
rna_clustering_algorithms-0.1.4.dist-info/top_level.txt
rna_clustering_algorithms-0.1.4.dist-info/RECORD
