Metadata-Version: 2.1
Name: rna_clustering_algorithms
Version: 0.1.4
Summary: A small example package
Author: Daniel Sutton, Laurits Madsen, Sebastian Svendsen, Valdemar Fuglsang
Classifier: Programming Language :: Python :: 3
Classifier: Operating System :: OS Independent
Classifier: License :: OSI Approved :: MIT License
Requires-Python: >=3.8
License-File: LICENSE
